django_migrate_fresh/__init__.py
django_migrate_fresh/manage.py
django_migrate_fresh/settings.py
django_migrate_fresh/__pycache__/__init__.cpython-313.pyc
django_migrate_fresh/django_migrate_fresh/__init__.py
django_migrate_fresh/django_migrate_fresh/asgi.py
django_migrate_fresh/django_migrate_fresh/settings.py
django_migrate_fresh/django_migrate_fresh/urls.py
django_migrate_fresh/django_migrate_fresh/wsgi.py
django_migrate_fresh/management/__init__.py
django_migrate_fresh/management/__pycache__/__init__.cpython-313.pyc
django_migrate_fresh/management/commands/__init__.py
django_migrate_fresh/management/commands/migrate_fresh.py
django_migrate_fresh/management/commands/__pycache__/__init__.cpython-313.pyc
django_migrate_fresh/management/commands/__pycache__/migrate_fresh.cpython-313.pyc
django_migrate_fresh-3.1.0.dist-info/licenses/LICENSE
django_migrate_fresh-3.1.0.dist-info/METADATA
django_migrate_fresh-3.1.0.dist-info/WHEEL
django_migrate_fresh-3.1.0.dist-info/top_level.txt
django_migrate_fresh-3.1.0.dist-info/RECORD
