Metadata-Version: 2.4
Name: django-migrate-fresh
Version: 3.1.0
Summary: Simple Django package for Laravel-style migrate:fresh functionality with backup support
Home-page: https://github.com/sepehr-mohseni/django-migrate-fresh
Author: Sepehr Mohseni
Author-email: Sepehr Mohseni <isepehrmohseni@gmail.com>
License: MIT
Project-URL: Homepage, https://github.com/sepehr-mohseni/django-migrate-fresh
Project-URL: Repository, https://github.com/sepehr-mohseni/django-migrate-fresh
Project-URL: Issues, https://github.com/sepehr-mohseni/django-migrate-fresh/issues
Keywords: django,migration,laravel,migrate,fresh,backup
Classifier: Development Status :: 5 - Production/Stable
Classifier: Environment :: Web Environment
Classifier: Framework :: Django
Classifier: Framework :: Django :: 3.2
Classifier: Framework :: Django :: 4.0
Classifier: Framework :: Django :: 4.1
Classifier: Framework :: Django :: 4.2
Classifier: Framework :: Django :: 5.0
Classifier: Intended Audience :: Developers
Classifier: License :: OSI Approved :: MIT License
Classifier: Operating System :: OS Independent
Classifier: Programming Language :: Python :: 3
Classifier: Programming Language :: Python :: 3.8
Classifier: Programming Language :: Python :: 3.9
Classifier: Programming Language :: Python :: 3.10
Classifier: Programming Language :: Python :: 3.11
Classifier: Programming Language :: Python :: 3.12
Classifier: Topic :: Software Development :: Libraries :: Python Modules
Requires-Python: >=3.8
License-File: LICENSE
Requires-Dist: Django>=3.2
Provides-Extra: test
Requires-Dist: pytest>=6.0; extra == "test"
Requires-Dist: pytest-django>=4.0; extra == "test"
Dynamic: author
Dynamic: home-page
Dynamic: license-file
Dynamic: requires-python
